[
  {
  "id":"1",
  "cancha":"Tenis",
  "parent_id":"0"
  },
  {
    "id":"2",
    "cancha":"Futbol 5",
    "parent_id":"0"
    },
  {
    "id":"3",
    "cancha":"Futbol 8",
    "parent_id":"0"
  },  
  {
    "id":"4",
    "cancha":"Padel",
    "parent_id":"0"
    },
  {
    "id":"5",
    "horario":"10",
    "parent_id":"1"
    },
  {
    "id":"6",
    "horario":"11",
    "parent_id":"1"
    },
  {
    "id":"7",
    "horario":"12",
    "parent_id":"1"
    },
  {
    "id":"8",
    "horario":"13",
    "parent_id":"1"
    },  
  {
    "id":"9",
    "horario":"14",
    "parent_id":"1"
    },
  {
    "id":"10",
    "horario":"15",
    "parent_id":"1"
    },  
  {
    "id":"11",
    "horario":"16",
    "parent_id":"1"
    },
  {
    "id":"12",
    "horario":"17",
    "parent_id":"1"
    }, 
  {
    "id":"13",
    "horario":"18",
    "parent_id":"1"
    },  
  {
    "id":"14",
    "horario":"19",
    "parent_id":"1"
    },  
  {
    "id":"15",
    "horario":"20",
    "parent_id":"1"
    },  
  {
    "id":"16",
    "horario":"21",
    "parent_id":"1"
    },  
  {
    "id":"17",
    "horario":"15",
    "parent_id":"2"
    },   
  {
    "id":"18",
    "horario":"16",
    "parent_id":"2"
    }, 
  {
    "id":"19",
    "horario":"17",
    "parent_id":"2"
    },  
  {
    "id":"20",
    "horario":"18",
    "parent_id":"2"
    },  
  {
    "id":"21",
    "horario":"19",
    "parent_id":"2"
    },   
  {
    "id":"22",
    "horario":"20",
    "parent_id":"2"
    }, 
  {
    "id":"23",
    "horario":"21",
    "parent_id":"2"
    },
  {
    "id":"24",
    "horario":"22",
    "parent_id":"2"
    },       
  {
    "id":"25",
    "horario":"14",
    "parent_id":"3"
    },  
  {
    "id":"26",
    "horario":"15",
    "parent_id":"3"
    },   
  {
    "id":"27",
    "horario":"16",
    "parent_id":"3"
    }, 
  {
    "id":"28",
    "horario":"17",
    "parent_id":"3"
    },
  {
    "id":"29",
    "horario":"18",
    "parent_id":"3"
    },
  {
    "id":"30",
    "horario":"19",
    "parent_id":"3"
    }, 
  {
    "id":"31",
    "horario":"20",
    "parent_id":"3"
    },
  {
    "id":"32",
    "horario":"21",
    "parent_id":"3"
    },
  {
    "id":"33",
    "horario":"10",
    "parent_id":"4"
    }, 
  {
    "id":"34",
    "horario":"11",
    "parent_id":"4"
    },
  {
    "id":"35",
    "horario":"12",
    "parent_id":"4"
    },
  {
    "id":"36",
    "horario":"14",
    "parent_id":"4"
    }, 
  {
    "id":"37",
    "horario":"15",
    "parent_id":"4"
    },
  {
    "id":"38",
    "horario":"16",
    "parent_id":"4"
    }, 
  {
    "id":"39",
    "horario":"17",
    "parent_id":"4"
    }, 
  {
    "id":"40",
    "horario":"18",
    "parent_id":"4"
    },
  {
    "id":"41",
    "horario":"19",
    "parent_id":"4"
    },  
  {
    "id":"42",
    "horario":"20",
    "parent_id":"4"
    }, 
  {
    "id":"43",
    "horario":"21",
    "parent_id":"4"
    },
  {
    "id":"44",
    "horario":"22",
    "parent_id":"4"
    }                
    
]